[
	{
		"id": 1,
		"title": "Frontend разработчик. JavaScript + React",
		"body": "Курс от WebCademy",
		"date": "15.01.2024",
		"link": "https://webcademy.ru/jscourse/",
		"linkName": "WebCademy"
	},
	{
		"id": 2,
		"title": "React",
		"body": "Самостоятельное изучение по открытым источникам",
		"date": "01.10.2023",
		"link": "https://www.youtube.com/@ArchakovBlog",
		"linkName": "YouTube"
	},
	{
		"id": 3,
		"title": "JavaScript",
		"body": "Фундаментальный JavaScript - Stepik",
		"date": "01.09.2023",
		"link": "https://stepik.org/course/114165",
		"linkName": "Stepik"
	},
	{
		"id": 4,
		"title": "HTML/CSS/JavaScript",
		"body": "Самостоятельное изучение по открытым источникам",
		"date": "01.09.2023",
		"link": "https://www.youtube.com/@WebCademy",
		"linkName": "YouTube"
	},
	{
		"id": 5,
		"title": "Flutter в мобильной разработке под iOS & Android",
		"body": "Skill-Branch - образовательная платформа",
		"date": "01.04.2021",
		"link": "https://skill-branch.ru/flutter",
		"linkName": "Skill-Branch"
	}
]
